apiCore/__init__.py
apiCore/core.py
apiCore/exceptions.py
api_hijacker-0.2.0.dist-info/METADATA
api_hijacker-0.2.0.dist-info/WHEEL
api_hijacker-0.2.0.dist-info/top_level.txt
api_hijacker-0.2.0.dist-info/RECORD
