Metadata-Version: 2.4
Name: api-hijacker
Version: 0.2.0
Summary: Create your own python library for interacting with any website's API.
Home-page: https://github.com/PolarisWater/api-hijacker
Author: PolarisWater
Author-email: 
Classifier: Programming Language :: Python :: 3
Classifier: License :: OSI Approved :: MIT License
Requires-Python: >=3.9
Requires-Dist: requests>=2.9.2
Requires-Dist: cloudscraper>=1.2.70
Dynamic: author
Dynamic: classifier
Dynamic: description
Dynamic: description-content-type
Dynamic: home-page
Dynamic: requires-dist
Dynamic: requires-python
Dynamic: summary
